{
  "project_info": {
    "project_number": "1044115533502",
    "project_id": "fantasy-hockey-mobile",
    "storage_bucket": "fantasy-hockey-mobile.appspot.com"
  },
  "client": [
    {
      "client_info": {
        "mobilesdk_app_id": "1:1044115533502:android:d3f793b542392f0491b8ef",
        "android_client_info": {
          "package_name": "com.fantasyhockeymobile"
        }
      },
      "oauth_client": [
        {
          "client_id": "1044115533502-d0desgpirmv3bngag557vr05fte2a1vo.apps.googleusercontent.com",
          "client_type": 3
        }
      ],
      "api_key": [
        {
          "current_key": "AIzaSyCX8DjS6gQbjrGueEq8B8Eo58qjkSAbQO8"
        }
      ],
      "services": {
        "appinvite_service": {
          "other_platform_oauth_client": [
            {
              "client_id": "1044115533502-d0desgpirmv3bngag557vr05fte2a1vo.apps.googleusercontent.com",
              "client_type": 3
            }
          ]
        }
      }
    }
  ],
  "configuration_version": "1"
}
